easyaudit_utils/__init__.py
easyaudit_utils/admin.py
easyaudit_utils/apps.py
easyaudit_utils/mixins.py
easyaudit_utils/models.py
easyaudit_utils/signals.py
easyaudit_utils/tests.py
easyaudit_utils/urls.py
easyaudit_utils/views.py
easyaudit_utils/migrations/__init__.py
easyaudit_utils/templates/easyaudit/_filters.html
easyaudit_utils/templates/easyaudit/crudevent_list.html
easyaudit_utils/templates/easyaudit/index.html
easyaudit_utils/templates/easyaudit/loginevent_list.html
easyaudit_utils/templates/easyaudit/requestevent_list.html
easyaudit_utils/templatetags/__init__.py
easyaudit_utils/templatetags/easyaudit_utils.py
django_easyaudit_utils-0.0.6.dist-info/LICENSE
django_easyaudit_utils-0.0.6.dist-info/METADATA
django_easyaudit_utils-0.0.6.dist-info/WHEEL
django_easyaudit_utils-0.0.6.dist-info/top_level.txt
django_easyaudit_utils-0.0.6.dist-info/RECORD
